infra/CLAUDE.md
infra/DEPENDENCIES.md
infra/ML_ARCHITECTURE_ANALYSIS.md
infra/OECT_UNIFIED_DATA_MANAGEMENT_SYSTEM.md
infra/__init__.py
infra/catalog_config20250929.yaml
infra/catalog_config20251101.yaml
infra/export_experiments_metadata.py
infra/logger_config.py
infra/main20250929.py
infra/数据处理记录.md
infra/catalog/CLAUDE.md
infra/catalog/PROCESS_DATA_PIPELINE_GUIDE.md
infra/catalog/REFACTORING_SUMMARY.md
infra/catalog/__init__.py
infra/catalog/__main__.py
infra/catalog/cli.py
infra/catalog/config.py
infra/catalog/models.py
infra/catalog/repository.py
infra/catalog/scanner.py
infra/catalog/service.py
infra/catalog/sync.py
infra/catalog/unified.py
infra/catalog/docs/V2_INTEGRATION_GUIDE.md
infra/catalog/docs/WORKFLOW_SEARCH_GUIDE.md
infra/catalog/example/catalog_config.yaml
infra/catalog/example/process_data_pipeline_example.py
infra/catalog/examples/v2_integration_demo.py
infra/catalog/feature_configs/README.md
infra/catalog/feature_configs/v2_ml_ready.yaml
infra/catalog/feature_configs/v2_quick_analysis.yaml
infra/catalog/feature_configs/v2_transfer_basic.yaml
infra/configs/assets.yaml
infra/configs/reports.yaml
infra/configs/slides.yaml
infra/csv2hdf/CLAUDE.md
infra/csv2hdf/__init__.py
infra/csv2hdf/batch_csvjson2hdf.py
infra/csv2hdf/clean_json.py
infra/csv2hdf/direct_csv2hdf.py
infra/csv2hdf/parallel_csv_processing.py
infra/experiment/CLAUDE.md
infra/experiment/__init__.py
infra/experiment/core/__init__.py
infra/experiment/core/experiment.py
infra/experiment/models/__init__.py
infra/experiment/models/attributes.py
infra/experiment/models/batch_data.py
infra/experiment/models/step_data.py
infra/experiment/models/workflow.py
infra/experiment/repositories/__init__.py
infra/experiment/repositories/base.py
infra/experiment/repositories/batch_hdf5_repository.py
infra/experiment/repositories/hdf5_repository.py
infra/experiment/services/__init__.py
infra/experiment/services/experiment_service.py
infra/experiment/services/workflow_service.py
oect_infra-3.3.0.dist-info/licenses/LICENSE
oect_infra-3.3.0.dist-info/METADATA
oect_infra-3.3.0.dist-info/WHEEL
oect_infra-3.3.0.dist-info/entry_points.txt
oect_infra-3.3.0.dist-info/top_level.txt
oect_infra-3.3.0.dist-info/RECORD
