Metadata-Version: 2.4
Name: oect-infra
Version: 3.3.0
Summary: OECT (Organic Electrochemical Transistor) data processing infrastructure for experiment management, feature engineering, and analysis
Author-email: lidonghao <lidonghao100@outlook.com>
License: MIT
Project-URL: Homepage, https://github.com/Durian-leader/oect-infra-package
Project-URL: Documentation, https://github.com/Durian-leader/oect-infra-package/blob/main/README.md
Project-URL: Repository, https://github.com/Durian-leader/oect-infra-package
Project-URL: Issues, https://github.com/Durian-leader/oect-infra-package/issues
Keywords: OECT,data-processing,scientific-computing,hdf5,feature-engineering,experiment-management,materials-science,electrochemistry
Classifier: Development Status :: 4 - Beta
Classifier: Intended Audience :: Science/Research
Classifier: License :: OSI Approved :: MIT License
Classifier: Operating System :: OS Independent
Classifier: Programming Language :: Python :: 3
Classifier: Programming Language :: Python :: 3.11
Classifier: Programming Language :: Python :: 3.12
Classifier: Topic :: Scientific/Engineering
Classifier: Topic :: Scientific/Engineering :: Chemistry
Classifier: Topic :: Scientific/Engineering :: Physics
Requires-Python: >=3.11
License-File: LICENSE
Requires-Dist: h5py>=3.8.0
Requires-Dist: pandas>=2.0.0
Requires-Dist: numpy>=1.24.0
Requires-Dist: matplotlib>=3.7.0
Requires-Dist: pydantic>=2.0.0
Requires-Dist: scipy>=1.10.0
Requires-Dist: scikit-learn>=1.3.0
Requires-Dist: PyYAML>=6.0
Requires-Dist: Pillow>=10.0.0
Requires-Dist: tabulate>=0.9.0
Requires-Dist: python-pptx>=0.6.21
Requires-Dist: numba>=0.57.0
Requires-Dist: opencv-python>=4.8.0
Requires-Dist: pyarrow>=14.0.0
Provides-Extra: dev
Requires-Dist: pytest>=7.0.0; extra == "dev"
Requires-Dist: pytest-cov>=4.0.0; extra == "dev"
Requires-Dist: black>=23.0.0; extra == "dev"
Requires-Dist: isort>=5.12.0; extra == "dev"
Requires-Dist: mypy>=1.0.0; extra == "dev"
Dynamic: license-file
